afusion/__init__.py
afusion/api.py
afusion/app.py
afusion/bonds.py
afusion/cli.py
afusion/execution.py
afusion/install.py
afusion/sequence_input.py
afusion/utils.py
afusion/visualization.py
afusion/__pycache__/__init__.cpython-310.pyc
afusion/__pycache__/cli.cpython-310.pyc
afusion-1.2.2.2.dist-info/LICENSE
afusion-1.2.2.2.dist-info/METADATA
afusion-1.2.2.2.dist-info/WHEEL
afusion-1.2.2.2.dist-info/entry_points.txt
afusion-1.2.2.2.dist-info/top_level.txt
afusion-1.2.2.2.dist-info/RECORD
