Metadata-Version: 2.1
Name: afusion
Version: 1.2.2.2
Summary: AFusion: AlphaFold 3 GUI & Toolkit with Visualization
Home-page: https://github.com/Hanziwww/AlphaFold3-GUI
Author: Han Wang
Author-email: marspenman@gmail.com
Classifier: Programming Language :: Python :: 3
Classifier: License :: OSI Approved :: GNU General Public License v3 (GPLv3)
Classifier: Operating System :: POSIX :: Linux
Requires-Python: >=3.10
License-File: LICENSE
Requires-Dist: streamlit
Requires-Dist: pandas
Requires-Dist: loguru
Requires-Dist: numpy
Requires-Dist: py3Dmol
Requires-Dist: biopython
Requires-Dist: plotly
